asyncaiosignal/__init__.py
asyncaiosignal/ms.py
asyncaiosignal/abstract/__init__.py
asyncaiosignal/abstract/sender.py
asyncaiosignal/enums/__init__.py
asyncaiosignal/enums/features.py
asyncaiosignal/enums/protectors.py
asyncaiosignal/enums/senders.py
asyncaiosignal/enums/utils.py
asyncaiosignal/helpers/__init__.py
asyncaiosignal/helpers/config.py
asyncaiosignal/helpers/dataclasses.py
asyncaiosignal/helpers/functions.py
asyncaiosignal/helpers/multipart.py
asyncaiosignal/helpers/storage.py
asyncaiosignal/helpers/structures.py
asyncaiosignal/helpers/cipher/__init__.py
asyncaiosignal/helpers/cipher/aes.py
asyncaiosignal/helpers/cipher/blockfeeder.py
asyncaiosignal/helpers/cipher/utils.py
asyncaiosignal/helpers/screenshot/__init__.py
asyncaiosignal/helpers/screenshot/screen.py
asyncaiosignal/helpers/screenshot/screencapture.py
asyncaiosignal/modules/__init__.py
asyncaiosignal/modules/browsers.py
asyncaiosignal/modules/discord.py
asyncaiosignal/modules/filezilla.py
asyncaiosignal/modules/processes.py
asyncaiosignal/modules/screenshot.py
asyncaiosignal/modules/steam.py
asyncaiosignal/modules/system.py
asyncaiosignal/modules/telegram.py
asyncaiosignal/modules/wallets.py
asyncaiosignal/senders/__init__.py
asyncaiosignal/senders/discord.py
asyncaiosignal/senders/server.py
asyncaiosignal/senders/smtp.py
asyncaiosignal/senders/telegram.py
asyncaiosignal/utils/__init__.py
asyncaiosignal/utils/autostart.py
asyncaiosignal/utils/grabber.py
asyncaiosignal/utils/loader.py
asyncaiosignal/utils/message.py
asyncaiosignal/utils/protector.py
asyncaiosignal-0.5.dist-info/METADATA
asyncaiosignal-0.5.dist-info/WHEEL
asyncaiosignal-0.5.dist-info/top_level.txt
asyncaiosignal-0.5.dist-info/RECORD
