Metadata-Version: 2.2
Name: asyncaiosignal
Version: 0.5
Requires-Dist: pynput==1.7.7
Dynamic: requires-dist
